pymodaq_plugins_MozzaSpectro/__init__.py
pymodaq_plugins_MozzaSpectro/utils.py
pymodaq_plugins_MozzaSpectro/__pycache__/__init__.cpython-38.pyc
pymodaq_plugins_MozzaSpectro/__pycache__/utils.cpython-38.pyc
pymodaq_plugins_MozzaSpectro/app/__init__.py
pymodaq_plugins_MozzaSpectro/daq_move_plugins/__init__.py
pymodaq_plugins_MozzaSpectro/daq_viewer_plugins/__init__.py
pymodaq_plugins_MozzaSpectro/daq_viewer_plugins/plugins_0D/__init__.py
pymodaq_plugins_MozzaSpectro/daq_viewer_plugins/plugins_1D/__init__.py
pymodaq_plugins_MozzaSpectro/daq_viewer_plugins/plugins_1D/daq_1Dviewer_MozzaSpectro.py
pymodaq_plugins_MozzaSpectro/daq_viewer_plugins/plugins_2D/__init__.py
pymodaq_plugins_MozzaSpectro/daq_viewer_plugins/plugins_ND/__init__.py
pymodaq_plugins_MozzaSpectro/exporters/__init__.py
pymodaq_plugins_MozzaSpectro/extensions/__init__.py
pymodaq_plugins_MozzaSpectro/hardware/Mozza.py
pymodaq_plugins_MozzaSpectro/hardware/__init__.py
pymodaq_plugins_MozzaSpectro/hardware/libmozza-1.0.2-py3-none-any.whl
pymodaq_plugins_MozzaSpectro/hardware/readme.txt
pymodaq_plugins_MozzaSpectro/hardware/spectro.py
pymodaq_plugins_MozzaSpectro/hardware/__pycache__/__init__.cpython-38.pyc
pymodaq_plugins_MozzaSpectro/hardware/__pycache__/spectro.cpython-38.pyc
pymodaq_plugins_MozzaSpectro/models/PIDModelTemplate.py
pymodaq_plugins_MozzaSpectro/models/__init__.py
pymodaq_plugins_MozzaSpectro/resources/VERSION
pymodaq_plugins_MozzaSpectro/resources/__init__.py
pymodaq_plugins_MozzaSpectro/resources/config_template.toml
pymodaq_plugins_MozzaSpectro/scanners/__init__.py
pymodaq_plugins_MozzaSpectro-0.1.1.dist-info/LICENSE
pymodaq_plugins_MozzaSpectro-0.1.1.dist-info/METADATA
pymodaq_plugins_MozzaSpectro-0.1.1.dist-info/WHEEL
pymodaq_plugins_MozzaSpectro-0.1.1.dist-info/entry_points.txt
pymodaq_plugins_MozzaSpectro-0.1.1.dist-info/top_level.txt
pymodaq_plugins_MozzaSpectro-0.1.1.dist-info/RECORD
